{
    "metadata": {
        "resultset": {
            "count": 4142,
            "offset": 0,
            "limit": 5000
        }
    },
"results":[{"categoria":"Localidad simple","centroide":{"lat":-43.380977129559,"lon":-65.838687742849},"departamento":{"id":"26042","nombre":"Gaiman"},"id":"26042040000","localidad_censal":{"id":"26042040","nombre":"28 de Julio"},"municipio":{"id":"265014","nombre":"28 de Julio"},"nombre":"28 DE JULIO","provincia":{"id":"26","nombre":"Chubut"}},{"categoria":"Entidad","centroide":{"lat":-45.782807331545,"lon":-67.503336787077},"departamento":{"id":"26021","nombre":"Escalante"},"id":"26021030001","localidad_censal":{"id":"26021030","nombre":"Comodoro Rivadavia"},"municipio":{"id":"260049","nombre":"Comodoro Rivadavia"},"nombre":"ACCESO NORTE","provincia":{"id":"26","nombre":"Chubut"}},{"categoria":"Localidad simple","centroide":{"lat":-44.705252113958,"lon":-70.846001013659},"departamento":{"id":"26084","nombre":"R\u00edo Senguer"},"id":"26084010000","localidad_censal":{"id":"26084010","nombre":"Aldea Apeleg"},"municipio":{"id":"260126","nombre":"Alto R\u00edo Senguer"},"nombre":"ALDEA APELEG","provincia":{"id":"26","nombre":"Chubut"}},{"categoria":"Localidad simple","centroide":{"lat":-45.561464468121,"lon":-71.518172616248},"departamento":{"id":"26084","nombre":"R\u00edo Senguer"},"id":"26084020000","localidad_censal":{"id":"26084020","nombre":"Aldea Beleiro"},"municipio":{"id":"268091","nombre":"Aldea Beleiro"},"nombre":"ALDEA BELEIRO","provincia":{"id":"26","nombre":"Chubut"}},{"categoria":"Localidad simple","centroide":{"lat":-43.234116595286,"lon":-69.71129377704},"departamento":{"id":"26056","nombre":"Langui\u00f1eo"},"id":"26056010000","localidad_censal":{"id":"26056010","nombre":"Aldea Epulef"},"municipio":{"id":null,"nombre":null},"nombre":"ALDEA EPULEF","provincia":{"id":"26","nombre":"Chubut"}},{"categoria":"Localidad simple","centroide":{"lat":-43.119818761402,"lon":-71.5588967458},"departamento":{"id":"26035","nombre":"Futaleuf\u00fa"},"id":"26035010000","localidad_censal":{"id":"26035010","nombre":"Aldea Escolar (Los R\u00e1pidos)"},"municipio":{"id":"260084","nombre":"Trevel\u00edn"},"nombre":"ALDEA ESCOLAR","provincia":{"id":"26","nombre":"Chubut"}},{"categoria":"Localidad simple","centroide":{"lat":-45.047641752038,"lon":-70.822755207712},"departamento":{"id":"26084","nombre":"R\u00edo Senguer"},"id":"26084030000","localidad_censal":{"id":"26084030","nombre":"Alto R\u00edo Senguer"},"municipio":{"id":"260126","nombre":"Alto R\u00edo Senguer"},"nombre":"ALTO RIO SENGUER","provincia":{"id":"26","nombre":"Chubut"}},{"categoria":"Localidad simple","centroide":{"lat":-42.011988696966,"lon":-65.306450092609},"departamento":{"id":"26007","nombre":"Biedma"},"id":"26007010000","localidad_censal":{"id":"26007010","nombre":"Arroyo Verde"},"municipio":{"id":null,"nombre":null},"nombre":"ARROYO VERDE","provincia":{"id":"26","nombre":"Chubut"}},{"categoria":"Localidad simple","centroide":{"lat":-45.736607545821,"lon":-67.485214728265},"departamento":{"id":"26021","nombre":"Escalante"},"id":"26021010000","localidad_censal":{"id":"26021010","nombre":"Astra"},"municipio":{"id":"260049","nombre":"Comodoro Rivadavia"},"nombre":"ASTRA","provincia":{"id":"26","nombre":"Chubut"}},{"categoria":"Localidad simple","centroide":{"lat":-45.114355282612,"lon":-66.53491661671},"departamento":{"id":"26021","nombre":"Escalante"},"id":"26021020000","localidad_censal":{"id":"26021020","nombre":"Bah\u00eda Bustamante"},"municipio":{"id":null,"nombre":null},"nombre":"BAHIA BUSTAMANTE","provincia":{"id":"26","nombre":"Chubut"}},{"categoria":"Entidad","centroide":{"lat":-45.824845463504,"lon":-67.461649598868},"departamento":{"id":"26021","nombre":"Escalante"},"id":"26021030016","localidad_censal":{"id":"26021030","nombre":"Comodoro Rivadavia"},"municipio":{"id":"260049","nombre":"Comodoro Rivadavia"},"nombre":"BARRIO 25 DE MAYO","provincia":{"id":"26","nombre":"Chubut"}},{"categoria":"Entidad","centroide":{"lat":-45.748250855901,"lon":-67.378650176946},"departamento":{"id":"26021","nombre":"Escalante"},"id":"26021030002","localidad_censal":{"id":"26021030","nombre":"Comodoro Rivadavia"},"municipio":{"id":"260049","nombre":"Comodoro Rivadavia"},"nombre":"BARRIO CALETA CORDOVA","provincia":{"id":"26","nombre":"Chubut"}},{"categoria":"Entidad","centroide":{"lat":-45.775727486738,"lon":-67.389560939103},"departamento":{"id":"26021","nombre":"Escalante"},"id":"26021030003","localidad_censal":{"id":"26021030","nombre":"Comodoro Rivadavia"},"municipio":{"id":"260049","nombre":"Comodoro Rivadavia"},"nombre":"BARRIO CALETA OLIVARES","provincia":{"id":"26","nombre":"Chubut"}},{"categoria":"Entidad","centroide":{"lat":-45.818047201795,"lon":-67.482028381133},"departamento":{"id":"26021","nombre":"Escalante"},"id":"26021030004","localidad_censal":{"id":"26021030","nombre":"Comodoro Rivadavia"},"municipio":{"id":"260049","nombre":"Comodoro Rivadavia"},"nombre":"BARRIO CASTELLI","provincia":{"id":"26","nombre":"Chubut"}},{"categoria":"Entidad","centroide":{"lat":-45.796933515978,"lon":-67.503853798744},"departamento":{"id":"26021","nombre":"Escalante"},"id":"26021030005","localidad_censal":{"id":"26021030","nombre":"Comodoro Rivadavia"},"municipio":{"id":"260049","nombre":"Comodoro Rivadavia"},"nombre":"BARRIO CIUDADELA","provincia":{"id":"26","nombre":"Chubut"}},{"categoria":"Entidad","centroide":{"lat":-45.793575685789,"lon":-67.503963495752},"departamento":{"id":"26021","nombre":"Escalante"},"id":"26021030006","localidad_censal":{"id":"26021030","nombre":"Comodoro Rivadavia"},"municipio":{"id":"260049","nombre":"Comodoro Rivadavia"},"nombre":"BARRIO GASODUCTO","provincia":{"id":"26","nombre":"Chubut"}},{"categoria":"Entidad","centroide":{"lat":-45.821712331945,"lon":-67.492120499473},"departamento":{"id":"26021","nombre":"Escalante"},"id":"26021030007","localidad_censal":{"id":"26021030","nombre":"Comodoro Rivadavia"},"municipio":{"id":"260049","nombre":"Comodoro Rivadavia"},"nombre":"BARRIO G\u00dcEMES","provincia":{"id":"26","nombre":"Chubut"}},{"categoria":"Entidad","centroide":{"lat":-45.828680617132,"lon":-67.542917580601},"departamento":{"id":"26021","nombre":"Escalante"},"id":"26021030008","localidad_censal":{"id":"26021030","nombre":"Comodoro Rivadavia"},"municipio":{"id":"260049","nombre":"Comodoro Rivadavia"},"nombre":"BARRIO LAPRIDA","provincia":{"id":"26","nombre":"Chubut"}},{"categoria":"Entidad","centroide":{"lat":-45.817196236331,"lon":-67.538403709651},"departamento":{"id":"26021","nombre":"Escalante"},"id":"26021030009","localidad_censal":{"id":"26021030","nombre":"Comodoro Rivadavia"},"municipio":{"id":"260049","nombre":"Comodoro Rivadavia"},"nombre":"BARRIO MANANTIAL ROSALES","provincia":{"id":"26","nombre":"Chubut"}},{"categoria":"Entidad","centroide":{"lat":-45.788020204419,"lon":-67.466685949282},"departamento":{"id":"26021","nombre":"Escalante"},"id":"26021030010","localidad_censal":{"id":"26021030","nombre":"Comodoro Rivadavia"},"municipio":{"id":"260049","nombre":"Comodoro Rivadavia"},"nombre":"BARRIO MILITAR - AEROPUERTO MILITAR","provincia":{"id":"26","nombre":"Chubut"}},{"categoria":"Entidad","centroide":{"lat":-45.795420585538,"lon":-67.472832043665},"departamento":{"id":"26021","nombre":"Escalante"},"id":"26021030011","localidad_censal":{"id":"26021030","nombre":"Comodoro Rivadavia"},"municipio":{"id":"260049","nombre":"Comodoro Rivadavia"},"nombre":"BARRIO PROSPERO PALAZZO","provincia":{"id":"26","nombre":"Chubut"}},{"categoria":"Entidad","centroide":{"lat":-45.79330952744,"lon":-67.409786122117},"departamento":{"id":"26021","nombre":"Escalante"},"id":"26021030012","localidad_censal":{"id":"26021030","nombre":"Comodoro Rivadavia"},"municipio":{"id":"260049","nombre":"Comodoro Rivadavia"},"nombre":"BARRIO RESTINGA ALI","provincia":{"id":"26","nombre":"Chubut"}},{"categoria":"Entidad","centroide":{"lat":-45.80420848638,"lon":-67.485501663995},"departamento":{"id":"26021","nombre":"Escalante"},"id":"26021030013","localidad_censal":{"id":"26021030","nombre":"Comodoro Rivadavia"},"municipio":{"id":"260049","nombre":"Comodoro Rivadavia"},"nombre":"BARRIO RODRIGUEZ PE\u00d1A","provincia":{"id":"26","nombre":"Chubut"}},{"categoria":"Entidad","centroide":{"lat":-45.845530761548,"lon":-67.514585299399},"departamento":{"id":"26021","nombre":"Escalante"},"id":"26021030014","localidad_censal":{"id":"26021030","nombre":"Comodoro Rivadavia"},"municipio":{"id":"260049","nombre":"Comodoro Rivadavia"},"nombre":"BARRIO SAAVEDRA","provincia":{"id":"26","nombre":"Chubut"}},{"categoria":"Entidad","centroide":{"lat":-45.819133351733,"lon":-67.502587140919},"departamento":{"id":"26021","nombre":"Escalante"},"id":"26021030015","localidad_censal":{"id":"26021030","nombre":"Comodoro Rivadavia"},"municipio":{"id":"260049","nombre":"Comodoro Rivadavia"},"nombre":"BARRIO SARMIENTO","provincia":{"id":"26","nombre":"Chubut"}},{"categoria":"Entidad","centroide":{"lat":-45.836738026383,"lon":-67.502111202691},"departamento":{"id":"26021","nombre":"Escalante"},"id":"26021030017","localidad_censal":{"id":"26021030","nombre":"Comodoro Rivadavia"},"municipio":{"id":"260049","nombre":"Comodoro Rivadavia"},"nombre":"BARRIO VILLA S.U.P.E.","provincia":{"id":"26","nombre":"Chubut"}},{"categoria":"Localidad simple","centroide":{"lat":-42.568389229153,"lon":-68.919091623714},"departamento":{"id":"26049","nombre":"Gastre"},"id":"26049010000","localidad_censal":{"id":"26049010","nombre":"Blancuntre"},"municipio":{"id":null,"nombre":null},"nombre":"BLANCUNTRE","provincia":{"id":"26","nombre":"Chubut"}},{"categoria":"Localidad simple","centroide":{"lat":-45.080422563331,"lon":-69.449777772128},"departamento":{"id":"26091","nombre":"Sarmiento"},"id":"26091010000","localidad_censal":{"id":"26091010","nombre":"Buen Pasto"},"municipio":{"id":"268119","nombre":"Buen Pasto"},"nombre":"BUEN PASTO","provincia":{"id":"26","nombre":"Chubut"}},{"categoria":"Localidad simple","centroide":{"lat":-42.068796126009,"lon":-71.215834313773},"departamento":{"id":"26014","nombre":"Cushamen"},"id":"26014010000","localidad_censal":{"id":"26014010","nombre":"Buenos Aires Chico"},"municipio":{"id":"260028","nombre":"El Mait\u00e9n"},"nombre":"BUENOS AIRES CHICO","provincia":{"id":"26","nombre":"Chubut"}},{"categoria":"Localidad simple","centroide":{"lat":-44.79829087317,"lon":-65.710599293495},"departamento":{"id":"26028","nombre":"Florentino Ameghino"},"id":"26028010000","localidad_censal":{"id":"26028010","nombre":"Camarones"},"municipio":{"id":"260063","nombre":"Camarones"},"nombre":"CAMARONES","provincia":{"id":"26","nombre":"Chubut"}},{"categoria":"Localidad simple","centroide":{"lat":-43.585688543731,"lon":-71.700902024502},"departamento":{"id":"26056","nombre":"Langui\u00f1eo"},"id":"26056020000","localidad_censal":{"id":"26056020","nombre":"Carrenleuf\u00fa"},"municipio":{"id":"268056","nombre":"Carrenleuf\u00fa"},"nombre":"CARRENLEUFU","provincia":{"id":"26","nombre":"Chubut"}},{"categoria":"Localidad simple","centroide":{"lat":-43.423319865399,"lon":-69.164092347675},"departamento":{"id":"26070","nombre":"Paso de Indios"},"id":"26070010000","localidad_censal":{"id":"26070010","nombre":"Cerro C\u00f3ndor"},"municipio":{"id":null,"nombre":null},"nombre":"CERRO CONDOR","provincia":{"id":"26","nombre":"Chubut"}},{"categoria":"Localidad simple","centroide":{"lat":-42.510531364836,"lon":-71.435154828866},"departamento":{"id":"26014","nombre":"Cushamen"},"id":"26014020000","localidad_censal":{"id":"26014020","nombre":"Cholila"},"municipio":{"id":"260014","nombre":"Cholila"},"nombre":"CHOLILA","provincia":{"id":"26","nombre":"Chubut"}},{"categoria":"Localidad simple","centroide":{"lat":-43.242597704833,"lon":-69.930218185607},"departamento":{"id":"26056","nombre":"Langui\u00f1eo"},"id":"26056030000","localidad_censal":{"id":"26056030","nombre":"Colan Conhu\u00e9"},"municipio":{"id":"268063","nombre":"Colan Conhu\u00e9"},"nombre":"COLAN CONHUE","provincia":{"id":"26","nombre":"Chubut"}},{"categoria":"Entidad","centroide":{"lat":-45.872984677806,"lon":-67.543055997943},"departamento":{"id":"26021","nombre":"Escalante"},"id":"26021030018","localidad_censal":{"id":"26021030","nombre":"Comodoro Rivadavia"},"municipio":{"id":"260049","nombre":"Comodoro Rivadavia"},"nombre":"COMODORO RIVADAVIA","provincia":{"id":"26","nombre":"Chubut"}},{"categoria":"Localidad simple","centroide":{"lat":-43.538002165733,"lon":-71.465961621584},"departamento":{"id":"26035","nombre":"Futaleuf\u00fa"},"id":"26035020000","localidad_censal":{"id":"26035020","nombre":"Corcovado"},"municipio":{"id":"260070","nombre":"Corcovado"},"nombre":"CORCOVADO","provincia":{"id":"26","nombre":"Chubut"}},{"categoria":"Localidad simple","centroide":{"lat":-42.601625583604,"lon":-70.457573727354},"departamento":{"id":"26014","nombre":"Cushamen"},"id":"26014025000","localidad_censal":{"id":"26014025","nombre":"Costa del Chubut"},"municipio":{"id":null,"nombre":null},"nombre":"COSTA DE CHUBUT","provincia":{"id":"26","nombre":"Chubut"}},{"categoria":"Localidad simple","centroide":{"lat":-42.176661102814,"lon":-70.662618842918},"departamento":{"id":"26014","nombre":"Cushamen"},"id":"26014030000","localidad_censal":{"id":"26014030","nombre":"Cushamen Centro"},"municipio":{"id":"268014","nombre":"Cushamen"},"nombre":"CUSHAMEN CENTRO","provincia":{"id":"26","nombre":"Chubut"}},{"categoria":"Localidad simple","centroide":{"lat":-45.790608915802,"lon":-67.673892572617},"departamento":{"id":"26021","nombre":"Escalante"},"id":"26021040000","localidad_censal":{"id":"26021040","nombre":"Diadema Argentina"},"municipio":{"id":"260049","nombre":"Comodoro Rivadavia"},"nombre":"DIADEMA ARGENTINA","provincia":{"id":"26","nombre":"Chubut"}},{"categoria":"Localidad simple","centroide":{"lat":-43.703284751354,"lon":-66.479400323535},"departamento":{"id":"26042","nombre":"Gaiman"},"id":"26042010000","localidad_censal":{"id":"26042010","nombre":"Dique Florentino Ameghino"},"municipio":{"id":"268028","nombre":"Dique Florentino Ameghino"},"nombre":"DIQUE FLORENTINO AMEGHINO","provincia":{"id":"26","nombre":"Chubut"}},{"categoria":"Localidad simple","centroide":{"lat":-45.58700843063,"lon":-71.029096842241},"departamento":{"id":"26084","nombre":"R\u00edo Senguer"},"id":"26084040000","localidad_censal":{"id":"26084040","nombre":"Doctor Ricardo Rojas"},"municipio":{"id":"268098","nombre":"Doctor Ricardo Rojas"},"nombre":"DOCTOR RICARDO ROJAS","provincia":{"id":"26","nombre":"Chubut"}},{"categoria":"Localidad simple","centroide":{"lat":-43.309297578868,"lon":-65.708738838569},"departamento":{"id":"26042","nombre":"Gaiman"},"id":"26042020000","localidad_censal":{"id":"26042020","nombre":"Dolavon"},"municipio":{"id":"260091","nombre":"Dolavon"},"nombre":"DOLAVON","provincia":{"id":"26","nombre":"Chubut"}},{"categoria":"Localidad simple","centroide":{"lat":-43.098070041959,"lon":-68.559603335495},"departamento":{"id":"26049","nombre":"Gastre"},"id":"26049020000","localidad_censal":{"id":"26049020","nombre":"El Escorial"},"municipio":{"id":null,"nombre":null},"nombre":"EL ESCORIAL","provincia":{"id":"26","nombre":"Chubut"}},{"categoria":"Localidad simple","centroide":{"lat":-42.067966663704,"lon":-71.52067083709},"departamento":{"id":"26014","nombre":"Cushamen"},"id":"26014040000","localidad_censal":{"id":"26014040","nombre":"El Hoyo"},"municipio":{"id":"260021","nombre":"El Hoyo"},"nombre":"EL HOYO","provincia":{"id":"26","nombre":"Chubut"}},{"categoria":"Localidad simple","centroide":{"lat":-42.054285435837,"lon":-71.167315330839},"departamento":{"id":"26014","nombre":"Cushamen"},"id":"26014050000","localidad_censal":{"id":"26014050","nombre":"El Mait\u00e9n"},"municipio":{"id":"260028","nombre":"El Mait\u00e9n"},"nombre":"EL MAITEN","provincia":{"id":"26","nombre":"Chubut"}},{"categoria":"Localidad simple","centroide":{"lat":-43.285293271254,"lon":-67.760311381965},"departamento":{"id":"26063","nombre":"M\u00e1rtires"},"id":"26063010000","localidad_censal":{"id":"26063010","nombre":"El Mirasol"},"municipio":{"id":null,"nombre":null},"nombre":"EL MIRASOL","provincia":{"id":"26","nombre":"Chubut"}},{"categoria":"Localidad simple","centroide":{"lat":-42.232924712347,"lon":-71.369506657951},"departamento":{"id":"26014","nombre":"Cushamen"},"id":"26014060000","localidad_censal":{"id":"26014060","nombre":"Epuy\u00e9n"},"municipio":{"id":"260035","nombre":"Epuy\u00e9n"},"nombre":"EPUYEN","provincia":{"id":"26","nombre":"Chubut"}},{"categoria":"Localidad simple","centroide":{"lat":-42.913323885829,"lon":-71.318511631928},"departamento":{"id":"26035","nombre":"Futaleuf\u00fa"},"id":"26035030000","localidad_censal":{"id":"26035030","nombre":"Esquel"},"municipio":{"id":"260077","nombre":"Esquel"},"nombre":"ESQUEL","provincia":{"id":"26","nombre":"Chubut"}},{"categoria":"Localidad simple","centroide":{"lat":-45.319271038369,"lon":-69.972112734968},"departamento":{"id":"26084","nombre":"R\u00edo Senguer"},"id":"26084050000","localidad_censal":{"id":"26084050","nombre":"Facundo"},"municipio":{"id":"268105","nombre":"Facundo"},"nombre":"FACUNDO","provincia":{"id":"26","nombre":"Chubut"}},{"categoria":"Localidad simple","centroide":{"lat":-42.391062000599,"lon":-70.578078439941},"departamento":{"id":"26014","nombre":"Cushamen"},"id":"26014065000","localidad_censal":{"id":"26014065","nombre":"Fofo Cahuel"},"municipio":{"id":null,"nombre":null},"nombre":"FOFO CAHUEL","provincia":{"id":"26","nombre":"Chubut"}},{"categoria":"Localidad simple","centroide":{"lat":-44.198855650099,"lon":-71.666668164139},"departamento":{"id":"26098","nombre":"Tehuelches"},"id":"26098010000","localidad_censal":{"id":"26098010","nombre":"Doctor Oscar Atilio Viglione (Frontera de R\u00edo Pico)"},"municipio":{"id":"268147","nombre":"Dr. Atilio Oscar Viglione"},"nombre":"FRONTERA DE RIO PICO","provincia":{"id":"26","nombre":"Chubut"}},{"categoria":"Localidad simple","centroide":{"lat":-43.288807480447,"lon":-65.492413500074},"departamento":{"id":"26042","nombre":"Gaiman"},"id":"26042030000","localidad_censal":{"id":"26042030","nombre":"Gaiman"},"municipio":{"id":"260098","nombre":"Gaiman"},"nombre":"GAIMAN","provincia":{"id":"26","nombre":"Chubut"}},{"categoria":"Localidad simple","centroide":{"lat":-42.523233028848,"lon":-68.282854228887},"departamento":{"id":"26105","nombre":"Telsen"},"id":"26105010000","localidad_censal":{"id":"26105010","nombre":"Gan Gan"},"municipio":{"id":"268126","nombre":"Gan Gan"},"nombre":"GAN GAN","provincia":{"id":"26","nombre":"Chubut"}},{"categoria":"Localidad simple","centroide":{"lat":-44.679578372866,"lon":-66.609736455023},"departamento":{"id":"26028","nombre":"Florentino Ameghino"},"id":"26028020000","localidad_censal":{"id":"26028020","nombre":"Garayalde"},"municipio":{"id":null,"nombre":null},"nombre":"GARAYALDE","provincia":{"id":"26","nombre":"Chubut"}},{"categoria":"Localidad simple","centroide":{"lat":-42.265620456543,"lon":-69.221097897766},"departamento":{"id":"26049","nombre":"Gastre"},"id":"26049030000","localidad_censal":{"id":"26049030","nombre":"Gastre"},"municipio":{"id":"268035","nombre":"Gastre"},"nombre":"GASTRE","provincia":{"id":"26","nombre":"Chubut"}},{"categoria":"Localidad simple","centroide":{"lat":-44.052982606318,"lon":-70.597920256446},"departamento":{"id":"26098","nombre":"Tehuelches"},"id":"26098020000","localidad_censal":{"id":"26098020","nombre":"Gobernador Costa"},"municipio":{"id":"260147","nombre":"Gobernador Costa"},"nombre":"GOBERNADOR COSTA","provincia":{"id":"26","nombre":"Chubut"}},{"categoria":"Localidad simple","centroide":{"lat":-42.726757894673,"lon":-70.535487612671},"departamento":{"id":"26014","nombre":"Cushamen"},"id":"26014070000","localidad_censal":{"id":"26014070","nombre":"Gualjaina"},"municipio":{"id":"265007","nombre":"Gualjaina"},"nombre":"GUALJAINA","provincia":{"id":"26","nombre":"Chubut"}},{"categoria":"Localidad simple","centroide":{"lat":-44.05450308615,"lon":-70.469842345027},"departamento":{"id":"26098","nombre":"Tehuelches"},"id":"26098030000","localidad_censal":{"id":"26098030","nombre":"Jos\u00e9 de San Mart\u00edn"},"municipio":{"id":"260154","nombre":"Jos\u00e9 de San Mart\u00edn"},"nombre":"JOSE DE SAN MARTIN","provincia":{"id":"26","nombre":"Chubut"}},{"categoria":"Entidad","centroide":{"lat":-45.770767961254,"lon":-67.435804674423},"departamento":{"id":"26021","nombre":"Escalante"},"id":"26021030021","localidad_censal":{"id":"26021030","nombre":"Comodoro Rivadavia"},"municipio":{"id":"260049","nombre":"Comodoro Rivadavia"},"nombre":"KM. 11 - CUARTELES","provincia":{"id":"26","nombre":"Chubut"}},{"categoria":"Entidad","centroide":{"lat":-45.831828125108,"lon":-67.491709642443},"departamento":{"id":"26021","nombre":"Escalante"},"id":"26021030022","localidad_censal":{"id":"26021030","nombre":"Comodoro Rivadavia"},"municipio":{"id":"260049","nombre":"Comodoro Rivadavia"},"nombre":"KM. 3 - GENERAL MOSCONI","provincia":{"id":"26","nombre":"Chubut"}},{"categoria":"Entidad","centroide":{"lat":-45.78755227892,"lon":-67.469573623597},"departamento":{"id":"26021","nombre":"Escalante"},"id":"26021030019","localidad_censal":{"id":"26021030","nombre":"Comodoro Rivadavia"},"municipio":{"id":"260049","nombre":"Comodoro Rivadavia"},"nombre":"KM. 5 - PRESIDENTE ORTIZ","provincia":{"id":"26","nombre":"Chubut"}},{"categoria":"Entidad","centroide":{"lat":-45.798898238596,"lon":-67.431497023044},"departamento":{"id":"26021","nombre":"Escalante"},"id":"26021030020","localidad_censal":{"id":"26021030","nombre":"Comodoro Rivadavia"},"municipio":{"id":"260049","nombre":"Comodoro Rivadavia"},"nombre":"KM. 8 - DON BOSCO","provincia":{"id":"26","nombre":"Chubut"}},{"categoria":"Localidad simple","centroide":{"lat":-45.946859419083,"lon":-71.264110664311},"departamento":{"id":"26084","nombre":"R\u00edo Senguer"},"id":"26084060000","localidad_censal":{"id":"26084060","nombre":"Lago Blanco"},"municipio":{"id":null,"nombre":null},"nombre":"LAGO BLANCO","provincia":{"id":"26","nombre":"Chubut"}},{"categoria":"Localidad simple","centroide":{"lat":-42.213535683015,"lon":-71.429662543355},"departamento":{"id":"26014","nombre":"Cushamen"},"id":"26014080000","localidad_censal":{"id":"26014080","nombre":"Lago Epuy\u00e9n"},"municipio":{"id":"260035","nombre":"Epuy\u00e9n"},"nombre":"LAGO EPUYEN","provincia":{"id":"26","nombre":"Chubut"}},{"categoria":"Localidad simple","centroide":{"lat":-42.067292313086,"lon":-71.598157562524},"departamento":{"id":"26014","nombre":"Cushamen"},"id":"26014090000","localidad_censal":{"id":"26014090","nombre":"Lago Puelo"},"municipio":{"id":"260042","nombre":"Lago Puelo"},"nombre":"LAGO PUELO","provincia":{"id":"26","nombre":"Chubut"}},{"categoria":"Localidad simple","centroide":{"lat":-43.250016851871,"lon":-71.351231844289},"departamento":{"id":"26035","nombre":"Futaleuf\u00fa"},"id":"26035040000","localidad_censal":{"id":"26035040","nombre":"Lago Rosario"},"municipio":{"id":"260084","nombre":"Trevel\u00edn"},"nombre":"LAGO ROSARIO","provincia":{"id":"26","nombre":"Chubut"}},{"categoria":"Localidad simple","centroide":{"lat":-42.71677928383,"lon":-69.18847239357},"departamento":{"id":"26049","nombre":"Gastre"},"id":"26049040000","localidad_censal":{"id":"26049040","nombre":"Lagunita Salada"},"municipio":{"id":null,"nombre":null},"nombre":"LAGUNITA SALADA","provincia":{"id":"26","nombre":"Chubut"}},{"categoria":"Localidad simple","centroide":{"lat":-43.722397963617,"lon":-67.286995666614},"departamento":{"id":"26063","nombre":"M\u00e1rtires"},"id":"26063020000","localidad_censal":{"id":"26063020","nombre":"Las Plumas"},"municipio":{"id":"268077","nombre":"Las Plumas"},"nombre":"LAS PLUMAS","provincia":{"id":"26","nombre":"Chubut"}},{"categoria":"Localidad simple","centroide":{"lat":-42.428862621632,"lon":-71.068395163034},"departamento":{"id":"26014","nombre":"Cushamen"},"id":"26014100000","localidad_censal":{"id":"26014100","nombre":"Leleque"},"municipio":{"id":null,"nombre":null},"nombre":"LELEQUE","provincia":{"id":"26","nombre":"Chubut"}},{"categoria":"Localidad simple","centroide":{"lat":-43.871192998158,"lon":-68.430116877651},"departamento":{"id":"26070","nombre":"Paso de Indios"},"id":"26070020000","localidad_censal":{"id":"26070020","nombre":"Los Altares"},"municipio":{"id":"268084","nombre":"Los Altares"},"nombre":"LOS ALTARES","provincia":{"id":"26","nombre":"Chubut"}},{"categoria":"Localidad simple","centroide":{"lat":-43.184714621062,"lon":-71.641391929516},"departamento":{"id":"26035","nombre":"Futaleuf\u00fa"},"id":"26035050000","localidad_censal":{"id":"26035050","nombre":"Los Cipreses"},"municipio":{"id":"260084","nombre":"Trevel\u00edn"},"nombre":"LOS CIPRESES","provincia":{"id":"26","nombre":"Chubut"}},{"categoria":"Localidad simple","centroide":{"lat":-43.866305411766,"lon":-69.044887090231},"departamento":{"id":"26070","nombre":"Paso de Indios"},"id":"26070030000","localidad_censal":{"id":"26070030","nombre":"Paso de Indios"},"municipio":{"id":"265021","nombre":"Paso de Indios"},"nombre":"PASO DE INDIOS","provincia":{"id":"26","nombre":"Chubut"}},{"categoria":"Localidad simple","centroide":{"lat":-42.737110995087,"lon":-69.611002087555},"departamento":{"id":"26056","nombre":"Langui\u00f1eo"},"id":"26056040000","localidad_censal":{"id":"26056040","nombre":"Paso del Sapo"},"municipio":{"id":"268070","nombre":"Paso del Sapo"},"nombre":"PASO DEL SAPO","provincia":{"id":"26","nombre":"Chubut"}},{"categoria":"Localidad simple","centroide":{"lat":-43.382120861886,"lon":-65.044932568367},"departamento":{"id":"26077","nombre":"Rawson"},"id":"26077010000","localidad_censal":{"id":"26077010","nombre":"Playa Magagna"},"municipio":{"id":"260112","nombre":"Rawson"},"nombre":"PLAYA MAGAGNA","provincia":{"id":"26","nombre":"Chubut"}},{"categoria":"Localidad simple","centroide":{"lat":-43.321940853022,"lon":-65.047598735098},"departamento":{"id":"26077","nombre":"Rawson"},"id":"26077020000","localidad_censal":{"id":"26077020","nombre":"Playa Uni\u00f3n"},"municipio":{"id":"260112","nombre":"Rawson"},"nombre":"PLAYA UNION","provincia":{"id":"26","nombre":"Chubut"}},{"categoria":"Localidad simple","centroide":{"lat":-42.755099678345,"lon":-65.042229817816},"departamento":{"id":"26007","nombre":"Biedma"},"id":"26007020000","localidad_censal":{"id":"26007020","nombre":"Puerto Madryn"},"municipio":{"id":"260007","nombre":"Puerto Madryn"},"nombre":"PUERTO MADRYN","provincia":{"id":"26","nombre":"Chubut"}},{"categoria":"Localidad simple","centroide":{"lat":-42.573617193104,"lon":-64.283689346734},"departamento":{"id":"26007","nombre":"Biedma"},"id":"26007030000","localidad_censal":{"id":"26007030","nombre":"Puerto Pir\u00e1mides"},"municipio":{"id":null,"nombre":null},"nombre":"PUERTO PIRAMIDE","provincia":{"id":"26","nombre":"Chubut"}},{"categoria":"Localidad simple","centroide":{"lat":-42.811590013144,"lon":-65.051417803805},"departamento":{"id":"26007","nombre":"Biedma"},"id":"26007040000","localidad_censal":{"id":"26007040","nombre":"Quintas El Mirador"},"municipio":{"id":"260007","nombre":"Puerto Madryn"},"nombre":"QUINTA EL MIRADOR","provincia":{"id":"26","nombre":"Chubut"}},{"categoria":"Localidad simple","centroide":{"lat":-45.936801918563,"lon":-67.565396023657},"departamento":{"id":"26021","nombre":"Escalante"},"id":"26021050000","localidad_censal":{"id":"26021050","nombre":"Rada Tilly"},"municipio":{"id":"260056","nombre":"Rada Tilly"},"nombre":"RADA TILLY","provincia":{"id":"26","nombre":"Chubut"}},{"categoria":"Localidad simple","centroide":{"lat":-43.301051677894,"lon":-65.095520234043},"departamento":{"id":"26077","nombre":"Rawson"},"id":"26077030000","localidad_censal":{"id":"26077030","nombre":"Rawson"},"municipio":{"id":"260112","nombre":"Rawson"},"nombre":"RAWSON","provincia":{"id":"26","nombre":"Chubut"}},{"categoria":"Localidad simple","centroide":{"lat":-42.645615895786,"lon":-65.064722967257},"departamento":{"id":"26007","nombre":"Biedma"},"id":"26007050000","localidad_censal":{"id":"26007050","nombre":"Reserva Area Protegida El Doradillo"},"municipio":{"id":"260007","nombre":"Puerto Madryn"},"nombre":"RESERVA AREA PROTEGIDA EL DORADILLO","provincia":{"id":"26","nombre":"Chubut"}},{"categoria":"Localidad simple","centroide":{"lat":-45.696453817174,"lon":-70.255980448255},"departamento":{"id":"26084","nombre":"R\u00edo Senguer"},"id":"26084070000","localidad_censal":{"id":"26084070","nombre":"R\u00edo Mayo"},"municipio":{"id":"260133","nombre":"R\u00edo Mayo"},"nombre":"RIO MAYO","provincia":{"id":"26","nombre":"Chubut"}},{"categoria":"Localidad simple","centroide":{"lat":-44.18299324135,"lon":-71.370056536087},"departamento":{"id":"26098","nombre":"Tehuelches"},"id":"26098040000","localidad_censal":{"id":"26098040","nombre":"R\u00edo Pico"},"municipio":{"id":"260161","nombre":"R\u00edo Pico"},"nombre":"RIO PICO","provincia":{"id":"26","nombre":"Chubut"}},{"categoria":"Localidad simple","centroide":{"lat":-45.590519720018,"lon":-69.07068251672},"departamento":{"id":"26091","nombre":"Sarmiento"},"id":"26091020000","localidad_censal":{"id":"26091020","nombre":"Sarmiento"},"municipio":{"id":"260140","nombre":"Sarmiento"},"nombre":"SARMIENTO","provincia":{"id":"26","nombre":"Chubut"}},{"categoria":"Localidad simple","centroide":{"lat":-43.493582081526,"lon":-70.813560832101},"departamento":{"id":"26056","nombre":"Langui\u00f1eo"},"id":"26056050000","localidad_censal":{"id":"26056050","nombre":"Tecka"},"municipio":{"id":"260105","nombre":"Tecka"},"nombre":"TECKA","provincia":{"id":"26","nombre":"Chubut"}},{"categoria":"Localidad simple","centroide":{"lat":-42.438751161421,"lon":-66.941427996482},"departamento":{"id":"26105","nombre":"Telsen"},"id":"26105020000","localidad_censal":{"id":"26105020","nombre":"Telsen"},"municipio":{"id":null,"nombre":null},"nombre":"TELSEN","provincia":{"id":"26","nombre":"Chubut"}},{"categoria":"Localidad simple","centroide":{"lat":-43.248353857031,"lon":-65.310381331969},"departamento":{"id":"26077","nombre":"Rawson"},"id":"26077040000","localidad_censal":{"id":"26077040","nombre":"Trelew"},"municipio":{"id":"260119","nombre":"Trelew"},"nombre":"TRELEW","provincia":{"id":"26","nombre":"Chubut"}},{"categoria":"Localidad simple","centroide":{"lat":-43.090871190598,"lon":-71.465485369954},"departamento":{"id":"26035","nombre":"Futaleuf\u00fa"},"id":"26035060000","localidad_censal":{"id":"26035060","nombre":"Trevel\u00edn"},"municipio":{"id":"260084","nombre":"Trevel\u00edn"},"nombre":"TREVELIN","provincia":{"id":"26","nombre":"Chubut"}},{"categoria":"Localidad simple","centroide":{"lat":-42.900637585807,"lon":-71.606153511372},"departamento":{"id":"26035","nombre":"Futaleuf\u00fa"},"id":"26035070000","localidad_censal":{"id":"26035070","nombre":"Villa Futalaufquen"},"municipio":{"id":null,"nombre":null},"nombre":"VILLA FUTALAUFQUEN","provincia":{"id":"26","nombre":"Chubut"}},{"categoria":"Localidad simple","centroide":{"lat":-42.767135445761,"lon":-68.875421794475},"departamento":{"id":"26049","nombre":"Gastre"},"id":"26049050000","localidad_censal":{"id":"26049050","nombre":"Yala Laubat"},"municipio":{"id":null,"nombre":null},"nombre":"YALA LAUBAT","provincia":{"id":"26","nombre":"Chubut"}}]}